descarts/__init__.py
descarts-0.0.1.dist-info/LICENSE
descarts-0.0.1.dist-info/WHEEL
descarts-0.0.1.dist-info/METADATA
descarts-0.0.1.dist-info/RECORD
