Metadata-Version: 2.1
Name: descarts
Version: 0.0.1
Summary: Data Science Algorithms for Time Series
License: Apache-2.0
Author: Your Name
Author-email: you@example.com
Requires-Python: >=3.7,<3.11
Classifier: License :: OSI Approved :: Apache Software License
Classifier: Programming Language :: Python :: 3
Classifier: Programming Language :: Python :: 3.10
Classifier: Programming Language :: Python :: 3.7
Classifier: Programming Language :: Python :: 3.8
Classifier: Programming Language :: Python :: 3.9
